ReduMetrics/__init__.py
ReduMetrics/exceptions.py
ReduMetrics/metrics/__init__.py
ReduMetrics/metrics/cdc.py
ReduMetrics/metrics/k_ncp.py
ReduMetrics/metrics/rta.py
ReduMetrics/metrics/spearman.py
ReduMetrics/metrics/ulse.py
ReduMetrics/metrics/utils/__init__.py
ReduMetrics/metrics/utils/knn.py
redumetrics-0.1.0.dist-info/licenses/LICENSE
redumetrics-0.1.0.dist-info/METADATA
redumetrics-0.1.0.dist-info/WHEEL
redumetrics-0.1.0.dist-info/top_level.txt
redumetrics-0.1.0.dist-info/RECORD
