Metadata-Version: 2.4
Name: redumetrics
Version: 0.1.0
Summary: Metrics to evaluate dimensionality reduction quality.
Author-email: David Hidalgo <davidht02@gmail.com>
License: MIT License
Project-URL: Homepage, https://github.com/tuusuario/ReduMetrics
Project-URL: Issues, https://github.com/tuusuario/ReduMetrics/issues
Classifier: Programming Language :: Python :: 3
Classifier: Programming Language :: Python :: 3 :: Only
Classifier: License :: OSI Approved :: MIT License
Classifier: Operating System :: OS Independent
Classifier: Topic :: Scientific/Engineering :: Information Analysis
Requires-Python: >=3.9
License-File: LICENSE
Requires-Dist: numpy>=1.21
Requires-Dist: scipy>=1.7
Requires-Dist: scikit-learn>=1.0
Dynamic: license-file
Dynamic: requires-python
